sherpa_streamlit/__init__.py
sherpa_streamlit/kairntech-1000-Blockmark.png
sherpa_streamlit/sherpa.py
sherpa_streamlit/util.py
sherpa_streamlit/visualizer.py
sherpa_streamlit-0.4.8.dist-info/LICENSE
sherpa_streamlit-0.4.8.dist-info/WHEEL
sherpa_streamlit-0.4.8.dist-info/METADATA
sherpa_streamlit-0.4.8.dist-info/RECORD
