Metadata-Version: 2.1
Name: sherpa-streamlit
Version: 0.4.8
Summary: Kairntech Sherpa building blocks for Streamlit apps
Home-page: https://github.com/oterrier/sherpa_streamlit/
Keywords: 
Author: Olivier Terrier
Author-email: oterrier@gmail.com
Requires-Python: >=3.7
Classifier: Intended Audience :: Information Technology
Classifier: Intended Audience :: Developers
Classifier: Intended Audience :: System Administrators
Classifier: Operating System :: OS Independent
Classifier: Topic :: Software Development :: Libraries :: Application Frameworks
Classifier: Topic :: Software Development :: Libraries :: Python Modules
Classifier: Topic :: Software Development :: Libraries
Classifier: Topic :: Software Development
Classifier: License :: OSI Approved :: MIT License
Classifier: Development Status :: 4 - Beta
Classifier: Programming Language :: Python :: 3.7
Requires-Dist: pandas==1.2.3
Requires-Dist: openpyxl==3.0.7
Requires-Dist: streamlit==1.19.0
Requires-Dist: st-annotated-text>=3.0.0
Requires-Dist: sherpa-client==0.12.6
Requires-Dist: collections-extended>=1.0.2
Requires-Dist: python-multipart
Requires-Dist: Pillow
Requires-Dist: plac
Requires-Dist: bs4
Requires-Dist: methodtools
Requires-Dist: shortuuid==1.0.8
Requires-Dist: flit ; extra == "dev"
Requires-Dist: pre-commit ; extra == "dev"
Requires-Dist: bump2version ; extra == "dev"
Requires-Dist: sphinx ; extra == "docs"
Requires-Dist: sphinx-rtd-theme ; extra == "docs"
Requires-Dist: m2r2 ; extra == "docs"
Requires-Dist: sphinxcontrib.apidoc ; extra == "docs"
Requires-Dist: jupyter_sphinx ; extra == "docs"
Requires-Dist: pytest ; extra == "test"
Requires-Dist: pytest-cov ; extra == "test"
Requires-Dist: pytest-flake8 ; extra == "test"
Requires-Dist: types-requests ; extra == "test"
Requires-Dist: flake8==3.9.2 ; extra == "test"
Requires-Dist: pytest-mypy ; extra == "test"
Requires-Dist: pytest-black ; extra == "test"
Requires-Dist: tox ; extra == "test"
Provides-Extra: dev
Provides-Extra: docs
Provides-Extra: test
